pypcmringbuffer/__init__.py
pypcmringbuffer/main.py
pypcmringbuffer-0.0.4.dist-info/licenses/LICENSE
pypcmringbuffer-0.0.4.dist-info/WHEEL
pypcmringbuffer-0.0.4.dist-info/METADATA
pypcmringbuffer-0.0.4.dist-info/RECORD
