Metadata-Version: 2.4
Name: pypcmringbuffer
Version: 0.0.4
Summary: A Python implementation of a PCM ring buffer
Author-email: lotcarnage <lotcarnage@gmail.com>
Requires-Python: >=3.11
License-File: LICENSE
Requires-Dist: numpy >=1.20
Project-URL: Repository, https://github.com/lotcarnage/pypcmringbuffer
